[{"timestamp":"2025-01-26T00:47:11.566Z","count":0,"uniques":0},{"timestamp":"2025-01-27T00:40:18.566Z","count":0,"uniques":0},{"timestamp":"2025-01-28T00:00:44.305Z","count":0,"uniques":0},{"timestamp":"2025-01-29T01:11:00.359Z","count":0,"uniques":0},{"timestamp":"2025-01-30T01:13:45.982Z","count":0,"uniques":0},{"timestamp":"2025-01-31T01:20:12.271Z","count":0,"uniques":0},{"timestamp":"2025-02-01T00:42:57.885Z","count":0,"uniques":0},{"timestamp":"2025-02-02T00:47:14.076Z","count":0,"uniques":0},{"timestamp":"2025-02-03T01:06:27.871Z","count":0,"uniques":0},{"timestamp":"2025-02-04T01:18:32.785Z","count":0,"uniques":0},{"timestamp":"2025-02-05T00:47:22.947Z","count":0,"uniques":0},{"timestamp":"2025-02-06T00:51:48.810Z","count":0,"uniques":0},{"timestamp":"2025-02-07T01:01:20.428Z","count":0,"uniques":0},{"timestamp":"2025-02-08T00:00:00.000Z","count":2,"uniques":1},{"timestamp":"2025-02-09T00:56:27.352Z","count":0,"uniques":0},{"timestamp":"2025-02-10T00:00:00.000Z","count":1,"uniques":1},{"timestamp":"2025-02-11T00:40:00.498Z","count":0,"uniques":0},{"timestamp":"2025-02-12T01:49:46.128Z","count":0,"uniques":0},{"timestamp":"2025-02-13T01:12:06.286Z","count":0,"uniques":0},{"timestamp":"2025-02-14T01:39:04.326Z","count":0,"uniques":0},{"timestamp":"2025-02-15T00:44:20.098Z","count":0,"uniques":0},{"timestamp":"2025-02-16T01:57:10.299Z","count":0,"uniques":0},{"timestamp":"2025-02-17T00:00:00.000Z","count":2,"uniques":1},{"timestamp":"2025-02-18T00:40:21.421Z","count":0,"uniques":0},{"timestamp":"2025-02-19T01:35:53.394Z","count":0,"uniques":0},{"timestamp":"2025-02-20T00:00:24.491Z","count":0,"uniques":0},{"timestamp":"2025-02-21T00:56:43.329Z","count":0,"uniques":0},{"timestamp":"2025-02-22T00:46:36.163Z","count":0,"uniques":0},{"timestamp":"2025-02-23T01:56:48.707Z","count":0,"uniques":0},{"timestamp":"2025-02-24T00:58:40.739Z","count":0,"uniques":0},{"timestamp":"2025-02-25T01:45:17.408Z","count":0,"uniques":0}]
