[{"timestamp":"2024-12-29T00:00:00.000Z","count":2,"uniques":1},{"timestamp":"2024-12-30T01:53:13.109Z","count":0,"uniques":0},{"timestamp":"2024-12-31T01:27:51.287Z","count":0,"uniques":0},{"timestamp":"2025-01-01T01:17:21.603Z","count":0,"uniques":0},{"timestamp":"2025-01-02T00:36:00.882Z","count":0,"uniques":0},{"timestamp":"2025-01-03T00:43:32.947Z","count":0,"uniques":0},{"timestamp":"2025-01-04T01:22:35.658Z","count":0,"uniques":0},{"timestamp":"2025-01-05T00:40:54.997Z","count":0,"uniques":0}]
