[{"timestamp":"2025-02-18T00:40:42.374Z","count":0,"uniques":0},{"timestamp":"2025-02-19T01:36:14.175Z","count":0,"uniques":0},{"timestamp":"2025-02-20T00:00:45.353Z","count":0,"uniques":0},{"timestamp":"2025-02-21T00:57:03.894Z","count":0,"uniques":0},{"timestamp":"2025-02-22T00:46:59.291Z","count":0,"uniques":0},{"timestamp":"2025-02-23T01:57:09.401Z","count":0,"uniques":0},{"timestamp":"2025-02-24T00:59:01.182Z","count":0,"uniques":0},{"timestamp":"2025-02-25T01:45:40.782Z","count":0,"uniques":0}]
