[{"timestamp":"2024-12-14T01:52:19.111Z","count":0,"uniques":0},{"timestamp":"2024-12-15T01:54:20.828Z","count":0,"uniques":0},{"timestamp":"2024-12-16T01:17:31.445Z","count":0,"uniques":0},{"timestamp":"2024-12-17T00:02:35.315Z","count":0,"uniques":0},{"timestamp":"2024-12-18T00:49:03.040Z","count":0,"uniques":0},{"timestamp":"2024-12-19T01:06:15.277Z","count":0,"uniques":0},{"timestamp":"2024-12-20T00:43:01.539Z","count":0,"uniques":0},{"timestamp":"2024-12-21T00:00:00.000Z","count":3,"uniques":1},{"timestamp":"2024-12-22T01:15:12.301Z","count":0,"uniques":0},{"timestamp":"2024-12-23T01:26:14.907Z","count":0,"uniques":0},{"timestamp":"2024-12-24T00:00:00.000Z","count":1,"uniques":1},{"timestamp":"2024-12-25T01:21:09.798Z","count":0,"uniques":0},{"timestamp":"2024-12-26T01:22:45.940Z","count":0,"uniques":0},{"timestamp":"2024-12-27T01:19:01.958Z","count":0,"uniques":0},{"timestamp":"2024-12-28T01:17:14.420Z","count":0,"uniques":0},{"timestamp":"2024-12-29T00:02:04.584Z","count":0,"uniques":0},{"timestamp":"2024-12-30T00:00:37.310Z","count":0,"uniques":0},{"timestamp":"2024-12-31T01:29:20.953Z","count":0,"uniques":0},{"timestamp":"2025-01-01T00:00:00.000Z","count":1,"uniques":1},{"timestamp":"2025-01-02T00:37:25.562Z","count":0,"uniques":0},{"timestamp":"2025-01-03T00:00:00.000Z","count":8,"uniques":4},{"timestamp":"2025-01-04T01:23:58.495Z","count":0,"uniques":0},{"timestamp":"2025-01-05T00:42:19.428Z","count":0,"uniques":0},{"timestamp":"2025-01-06T00:00:00.000Z","count":4,"uniques":2},{"timestamp":"2025-01-07T00:01:25.466Z","count":0,"uniques":0},{"timestamp":"2025-01-08T00:01:16.296Z","count":0,"uniques":0},{"timestamp":"2025-01-09T00:43:56.874Z","count":0,"uniques":0},{"timestamp":"2025-01-10T00:00:00.000Z","count":1,"uniques":1},{"timestamp":"2025-01-11T01:13:40.107Z","count":0,"uniques":0},{"timestamp":"2025-01-12T00:01:24.313Z","count":0,"uniques":0},{"timestamp":"2025-01-13T00:47:14.112Z","count":0,"uniques":0}]
