[{"timestamp":"2024-04-15T00:00:00.000Z","count":4,"uniques":2},{"timestamp":"2024-04-16T00:00:00.000Z","count":1,"uniques":1},{"timestamp":"2024-04-17T00:00:00.000Z","count":4,"uniques":2},{"timestamp":"2024-04-18T00:00:00.000Z","count":3,"uniques":2},{"timestamp":"2024-04-19T00:00:00.000Z","count":4,"uniques":2},{"timestamp":"2024-04-20T00:00:00.000Z","count":4,"uniques":2},{"timestamp":"2024-04-21T00:32:50.408Z","count":0,"uniques":0},{"timestamp":"2024-04-22T01:22:37.609Z","count":0,"uniques":0},{"timestamp":"2024-04-23T00:00:00.000Z","count":2,"uniques":2},{"timestamp":"2024-04-24T00:00:00.000Z","count":6,"uniques":1},{"timestamp":"2024-04-25T00:00:00.000Z","count":4,"uniques":2},{"timestamp":"2024-04-26T00:00:00.000Z","count":1,"uniques":1},{"timestamp":"2024-04-27T00:00:00.000Z","count":1,"uniques":1},{"timestamp":"2024-04-28T00:00:00.000Z","count":3,"uniques":1},{"timestamp":"2024-04-29T00:00:00.000Z","count":4,"uniques":2},{"timestamp":"2024-04-30T01:18:59.771Z","count":0,"uniques":0},{"timestamp":"2024-05-01T00:00:00.000Z","count":1,"uniques":1},{"timestamp":"2024-05-02T00:00:00.000Z","count":1,"uniques":1},{"timestamp":"2024-05-03T00:52:33.938Z","count":0,"uniques":0},{"timestamp":"2024-05-04T00:42:30.690Z","count":0,"uniques":0},{"timestamp":"2024-05-05T00:00:00.000Z","count":21,"uniques":1},{"timestamp":"2024-05-06T00:00:00.000Z","count":8,"uniques":3},{"timestamp":"2024-05-07T00:00:00.000Z","count":3,"uniques":1},{"timestamp":"2024-05-08T00:25:01.106Z","count":0,"uniques":0},{"timestamp":"2024-05-09T01:22:16.422Z","count":0,"uniques":0},{"timestamp":"2024-05-10T00:00:00.000Z","count":3,"uniques":1},{"timestamp":"2024-05-11T00:40:32.361Z","count":0,"uniques":0},{"timestamp":"2024-05-12T00:00:00.000Z","count":6,"uniques":2},{"timestamp":"2024-05-13T00:44:19.480Z","count":0,"uniques":0},{"timestamp":"2024-05-14T01:23:00.510Z","count":0,"uniques":0},{"timestamp":"2024-05-15T01:24:15.898Z","count":0,"uniques":0}]
